elasticwriter/__init__.py
elasticwriter/elasticwriter.py
elasticwriter-2.2.1.dist-info/METADATA
elasticwriter-2.2.1.dist-info/WHEEL
elasticwriter-2.2.1.dist-info/top_level.txt
elasticwriter-2.2.1.dist-info/RECORD
